{
    "retCode": "200",
    "retMsg": "3",
    "data": {
        "data": [
            {
                "ROWNO": 1,
                "BAB001": 20041350,
                "AAB004": "兴化市大邹中心卫生院",
                "AAE140": "210",
                "AAC050": "变更类型",
                "AAE160": "变更原因",
                "AAE035": 20051116,
                "AAE011": "经办人",
                "AAE036": 20051116
            },
            {
                "ROWNO": 2,
                "BAB001": 20041350,
                "AAB004": "兴化市大邹中心卫生院",
                "AAE140": "210",
                "AAC050": "变更类型",
                "AAE160": "变更原因",
                "AAE035": 20051116,
                "AAE011": "经办人",
                "AAE036": 20051116
            }
        ],
        "pageSize": "2",
        "pageNumber": "1",
        "totalPage": "2"
    }
}